hightea/plotting/_MeasurementTools.py
hightea/plotting/__init__.py
hightea/plotting/plotting.py
hightea/plotting/run.py
hightea/plotting/stripper.py
hightea_plotting-0.3.5.dist-info/METADATA
hightea_plotting-0.3.5.dist-info/WHEEL
hightea_plotting-0.3.5.dist-info/top_level.txt
hightea_plotting-0.3.5.dist-info/RECORD
