Metadata-Version: 2.1
Name: hightea-plotting
Version: 0.3.5
Summary: Plotting routines for hightea project
Home-page: https://github.com/HighteaCollaboration/hightea-plotting
Author: Hightea Collaboration
Author-email: hightea@hep.phy.cam.ac.uk
License: MIT
Requires-Python: ~=3.7
Requires-Dist: pathlib2
Requires-Dist: matplotlib
Requires-Dist: numpy
Requires-Dist: pandas
Requires-Dist: more-itertools
